queky/__init__.py
queky/constants.py
queky/main.py
queky/utils.py
queky/assets/data.json
queky-0.1.2.2.dist-info/LICENSE
queky-0.1.2.2.dist-info/METADATA
queky-0.1.2.2.dist-info/WHEEL
queky-0.1.2.2.dist-info/entry_points.txt
queky-0.1.2.2.dist-info/top_level.txt
queky-0.1.2.2.dist-info/RECORD
