Metadata-Version: 2.1
Name: queky
Version: 0.1.2.2
Summary: Si Un Problema Puede Solucionarse, Entonces No Vale La Pena Preocuparse Por El.
Author: Pablo Escobar
License: MIT
Classifier: Programming Language :: Python :: 3
Classifier: License :: OSI Approved :: MIT License
Classifier: Operating System :: OS Independent
License-File: LICENSE
Requires-Dist: pyperclip
Requires-Dist: google-generativeai
Requires-Dist: pyautogui
